pytwanalysis/__init__.py
pytwanalysis/py_twitter_analysis.py
pytwanalysis/py_twitter_db.py
pytwanalysis/py_twitter_graphs.py
pytwanalysis/py_twitter_topics.py
pytwanalysis-0.0.6.dist-info/LICENSE
pytwanalysis-0.0.6.dist-info/METADATA
pytwanalysis-0.0.6.dist-info/WHEEL
pytwanalysis-0.0.6.dist-info/top_level.txt
pytwanalysis-0.0.6.dist-info/RECORD
