Metadata-Version: 2.1
Name: pytwanalysis
Version: 0.0.6
Summary: A tool to gather, discover, and analyze Twitter data using a combination of graph-clustering and topic modeling techniques with the goal of semantically grouping tweet messages together.
Home-page: https://github.com/lianogueira/pytwanalysis
Author: Lia Nogueira
License: UNKNOWN
Project-URL: Source Code, https://github.com/lianogueira/pytwanalysis
Project-URL: Documentation, https://lianogueira.github.io/pytwanalysis-documentation/
Platform: UNKNOWN
Classifier: Programming Language :: Python :: 3.7
Classifier: Operating System :: OS Independent
Classifier: Development Status :: 3 - Alpha
Classifier: Intended Audience :: Science/Research
